HISTORY.rst
LICENSE
MANIFEST.in
README.rst
setup.cfg
setup.py
docs/Makefile
docs/conf.py
docs/history.rst
docs/index.rst
docs/installation.rst
docs/readme.rst
docs/usage.rst
putshebang/__init__.py
putshebang/__main__.py
putshebang/_data.py
putshebang/file.py
putshebang/langs.json
putshebang/shebangs.py
putshebang.egg-info/PKG-INFO
putshebang.egg-info/SOURCES.txt
putshebang.egg-info/dependency_links.txt
putshebang.egg-info/entry_points.txt
putshebang.egg-info/not-zip-safe
putshebang.egg-info/requires.txt
putshebang.egg-info/top_level.txt
tests/__init__.py
tests/test_shebangs.py