Metadata-Version: 1.1
Name: putshebang
Version: 0.1.5
Summary: A small tool that helps in adding the appropriate shebang
Home-page: https://github.com/faddyy/putshebang
Author: Fady Adel
Author-email: 2masadel@gmail.com
License: GNU General Public License v3
Keywords: putshebang add put shebang
Platform: unix
Classifier: Development Status :: 3 - Alpha
Classifier: Intended Audience :: Developers
Classifier: License :: OSI Approved :: GNU General Public License v3 (GPLv3)
Classifier: Natural Language :: English
Classifier: Programming Language :: Python :: 2
Classifier: Programming Language :: Python :: 2.6
Classifier: Programming Language :: Python :: 2.7
Classifier: Programming Language :: Python :: 3
Classifier: Programming Language :: Python :: 3.3
Classifier: Programming Language :: Python :: 3.4
Classifier: Programming Language :: Python :: 3.5
Classifier: Programming Language :: Python :: 3.6
